django_foreignform-0.0.9.dist-info/METADATA
django_foreignform-0.0.9.dist-info/RECORD
django_foreignform-0.0.9.dist-info/WHEEL
django_foreignform-0.0.9.dist-info/top_level.txt
foreignform/__init__.py
foreignform/apps.py
foreignform/fields.py
foreignform/mixins.py
foreignform/models.py
foreignform/widgets.py
foreignform/migrations/__init__.py
foreignform/static/foreignform/css/codemirror.css
foreignform/static/foreignform/css/main-change.css
foreignform/static/foreignform/fonts/bootstrap/glyphicons-halflings-regular.eot
foreignform/static/foreignform/fonts/bootstrap/glyphicons-halflings-regular.svg
foreignform/static/foreignform/fonts/bootstrap/glyphicons-halflings-regular.ttf
foreignform/static/foreignform/fonts/bootstrap/glyphicons-halflings-regular.woff
foreignform/static/foreignform/fonts/bootstrap/glyphicons-halflings-regular.woff2
foreignform/static/foreignform/js/codemirror.js
foreignform/static/foreignform/js/main-add.js
foreignform/static/foreignform/js/main-change.js
foreignform/templates/foreignform/add.html
foreignform/templates/foreignform/change.html
